httpfpt-0.8.1.dist-info/METADATA
httpfpt-0.8.1.dist-info/WHEEL
httpfpt-0.8.1.dist-info/entry_points.txt
httpfpt-0.8.1.dist-info/licenses/LICENSE
httpfpt/__init__.py
httpfpt/cli.py
httpfpt/common/__init__.py
httpfpt/common/env_handler.py
httpfpt/common/errors.py
httpfpt/common/excel_handler.py
httpfpt/common/json_handler.py
httpfpt/common/log.py
httpfpt/common/send_request.py
httpfpt/common/toml_handler.py
httpfpt/common/variable_cache.py
httpfpt/common/yaml_handler.py
httpfpt/conftest.py
httpfpt/core/__init__.py
httpfpt/core/allure_env/environment.properties
httpfpt/core/auth.yaml
httpfpt/core/conf.toml
httpfpt/core/get_conf.py
httpfpt/core/global_vars.yaml
httpfpt/core/hooks.py
httpfpt/core/path_conf.py
httpfpt/core/run_env/dev.env
httpfpt/core/run_env/pro.env
httpfpt/data/__init__.py
httpfpt/data/test_data/test_project/api_testcase_template.yaml
httpfpt/data/test_data/test_project/only_skip.yml
httpfpt/data/test_data/test_project/upload_file.json
httpfpt/db/__init__.py
httpfpt/db/mysql.py
httpfpt/db/redis.py
httpfpt/enums/__init__.py
httpfpt/enums/allure_severity_type.py
httpfpt/enums/assert_type.py
httpfpt/enums/case_data_type.py
httpfpt/enums/email_type.py
httpfpt/enums/query_fetch_type.py
httpfpt/enums/request/__init__.py
httpfpt/enums/request/auth.py
httpfpt/enums/request/body.py
httpfpt/enums/request/engin.py
httpfpt/enums/request/method.py
httpfpt/enums/setup_type.py
httpfpt/enums/sql_type.py
httpfpt/enums/teardown_type.py
httpfpt/enums/var_type.py
httpfpt/py.typed
httpfpt/pytest.ini
httpfpt/run.py
httpfpt/schemas/__init__.py
httpfpt/schemas/case_data.py
httpfpt/templates/email_notification.html
httpfpt/templates/email_report.html
httpfpt/utils/__init__.py
httpfpt/utils/allure_control.py
httpfpt/utils/assert_control.py
httpfpt/utils/auth_plugins.py
httpfpt/utils/case_auto_generator.py
httpfpt/utils/cli/__init__.py
httpfpt/utils/cli/about_testcase.py
httpfpt/utils/cli/import_case_data.py
httpfpt/utils/cli/new_project.py
httpfpt/utils/cli/version.py
httpfpt/utils/data_manage/__init__.py
httpfpt/utils/data_manage/apifox.py
httpfpt/utils/data_manage/base_format.py
httpfpt/utils/data_manage/git_repo.py
httpfpt-0.8.1.dist-info/RECORD
