Metadata-Version: 2.1
Name: httpfpt
Version: 0.8.1
Summary: 基于 HTTP 请求的快速数据驱动 pytest 接口自动化测试框架
Author-Email: Wu Clan <jianhengwu0407@gmail.com>
License: MIT
Classifier: License :: OSI Approved :: MIT License
Classifier: Programming Language :: Python :: 3 :: Only
Classifier: Programming Language :: Python :: 3.8
Classifier: Programming Language :: Python :: 3.9
Classifier: Programming Language :: Python :: 3.10
Classifier: Programming Language :: Python :: 3.11
Classifier: Programming Language :: Python :: 3.12
Project-URL: homepage, https://wu-clan.github.io/httpfpt_docs/
Project-URL: repository, https://github.com/wu-clan/httpfpt
Requires-Python: >=3.10
Requires-Dist: allure-pytest==2.13.2
Requires-Dist: cache3>=0.4.3
Requires-Dist: cappa==0.17.1
Requires-Dist: cryptography>=41.0.6
Requires-Dist: dbutils>=3.0.2
Requires-Dist: dirty-equals==0.7.1
Requires-Dist: faker>=13.15.0
Requires-Dist: httpx>=0.23.0
Requires-Dist: jinja2>=3.1.3
Requires-Dist: loguru>=0.6.0
Requires-Dist: pre-commit>=3.2.2
Requires-Dist: py==1.11.0
Requires-Dist: pydantic>=2.6.0
Requires-Dist: pymysql>=0.9.3
Requires-Dist: pytest<=8.0.2,>=8.0.0
Requires-Dist: pytest-html==4.0.0
Requires-Dist: pytest-metadata==3.0.0
Requires-Dist: pytest-pretty>=1.2.0
Requires-Dist: python-dotenv>=0.20.0
Requires-Dist: python-jsonpath>=1.0.0
Requires-Dist: pyyaml>=6.0.1
Requires-Dist: redis[hiredis]>=5.0.1
Requires-Dist: requests>=2.31.0
Requires-Dist: rtoml==0.9.0
Requires-Dist: xlrd==1.2.0
Requires-Dist: eval_type_backport>=0.1.3
Requires-Dist: stamina>=24.1.0
Requires-Dist: typing_extensions>=4.8.0
Requires-Dist: jsonschema>=4.21.1
Requires-Dist: pygments>=2.17.2
Requires-Dist: glom==23.5.0
